README.md
setup.py
deploy/chutils.py
deploy/deploy.py
deploy/permissions.py
ems_deploy.egg-info/PKG-INFO
ems_deploy.egg-info/SOURCES.txt
ems_deploy.egg-info/dependency_links.txt
ems_deploy.egg-info/entry_points.txt
ems_deploy.egg-info/requires.txt
ems_deploy.egg-info/top_level.txt