Metadata-Version: 2.1
Name: ems-deploy
Version: 0.0.13
Summary: A small deploy utility package
Home-page: https://github.com/
Author: Jesper Halkjær Jensen
Author-email: gedemagt@gmail.com
License: MIT
Platform: UNKNOWN
Requires-Python: >=3.6
